inner_point_sdp/__init__.py
inner_point_sdp/sdp.py
inner_point_sdp-0.0.1.dist-info/LICENSE
inner_point_sdp-0.0.1.dist-info/METADATA
inner_point_sdp-0.0.1.dist-info/WHEEL
inner_point_sdp-0.0.1.dist-info/top_level.txt
inner_point_sdp-0.0.1.dist-info/RECORD
