Metadata-Version: 2.1
Name: inner-point-sdp
Version: 0.0.1
Summary: Inner Point method for semi definite programmes
Home-page: https://github.com/pypa/sampleproject
Author: Eduard Bopp
Author-email: eduard.bopp@hhu.de
License: UNKNOWN
Project-URL: Bug Tracker, https://github.com/pypa/sampleproject/issues
Platform: UNKNOWN
Classifier: Programming Language :: Python :: 3
Classifier: License :: OSI Approved :: MIT License
Classifier: Operating System :: OS Independent
Requires-Python: >=3.6
License-File: LICENSE
